{
  "international_leagues": [
    "Australia Men's v England",
    "Australia Men's v NZ",
    "Australia v South Africa",
    "Diamond Challenge",
    "England Roses vs Australian Diamonds",
    "England Series",
    "England in Australia",
    "England in New Zealand",
    "International Netball Super Series",
    "January Netball Quad Series",
    "January Netball Quad Series Finals",
    "NWC Medals",
    "NWC Placings",
    "NWC Play-offs and Placings",
    "NWC Playoffs and Placings",
    "NWC Preliminaries Stage 1 and 2",
    "NWC Preliminary",
    "NWC Qualification",
    "NWC Regional Qualifiers",
    "NWC Regional Qualifiers Finals",
    "Nations Cup",
    "Netball Nations Cup",
    "Netball Nations Cup Finals",
    "Netball Quad Series - August",
    "Netball Quad Series - January",
    "Netball Quad Series - September",
    "Netball South Africa President XII",
    "Netball World Cup (NWC)",
    "PNS - Place final",
    "PNS - Place/Final",
    "PNS - PlaceFinal",
    "PNS Place final",
    "PNS PlaceFinal",
    "Pac Netball Series",
    "Pac. Netball Series",
    "Pacific Netball Series (PNS)",
    "Play-offs and Placings",
    "Playoffs and Placings",
    "Preliminaries Stage 1 and 2",
    "Quad Supersport testing",
    "Silver Ferns Internationals",
    "Silver Ferns Tour of Wales",
    "Super Club",
    "Super Club Finals",
    "Vitality Super League"
  ],
  "australian_leagues": [
    "#TeamGirls Cup A",
    "#TeamGirls Cup B",
    "#TeamGirls Cup Finals",
    "Australian Netball Championships",
    "Australian Netball Championships Finals",
    "Bushfire Relief",
    "Bushfire Relief 2020",
    "England in Australia",
    "Super Netball",
    "Super Netball Finals",
    "TeamGirls Cup A",
    "TeamGirls Cup B",
    "TeamGirls Cup Finals",
    "TeamGirls Cup Pool A",
    "TeamGirls Cup Pool B"
  ],
  "nz_leagues": [
    "ANZ Championship",
    "ANZ Finals",
    "ANZ Premiership",
    "ANZ Premiership Finals",
    "Beko National League",
    "Beko Netball League",
    "Beko Netball League Final",
    "Cadbury Netball Series",
    "College Netball",
    "Constellation Cup",
    "Group Championships",
    "Group Championships Under 23",
    "Lion Foundation National Champs",
    "NNZ Pre-Season",
    "NZ Secondary Schools  Finals",
    "NZ Secondary Schools  Pool Phase 1",
    "NZ Secondary Schools  Pool Phase 2",
    "NZ Secondary Schools - Finals",
    "NZ Secondary Schools - Pool Phase 1",
    "NZ Secondary Schools - Pool Phase 2",
    "NZ Secondary Schools Champs",
    "NZ Secondary Schools Champs Finals",
    "NZ Secondary Schools Finals",
    "NZ Secondary Schools Pool Phase 1",
    "NZ Secondary Schools Pool Phase 2",
    "National Netball League",
    "National Netball League Final",
    "Netball NZ National Champs",
    "Netball NZ Open Champs",
    "Netball NZ Secondary School",
    "Netball NZ Secondary Schools",
    "Netball NZ U19 Champs",
    "Pita Pit NZ Netball Champs",
    "Pita Pit NZ Secondary Schools Netball Champs  Fin",
    "Pita Pit NZ Secondary Schools Netball Champs  R1",
    "Pita Pit NZ Secondary Schools Netball Champs  R2",
    "Pita Pit NZ Secondary Schools Netball Champs - Fin",
    "Pita Pit NZ Secondary Schools Netball Champs - R1",
    "Pita Pit NZ Secondary Schools Netball Champs - R2",
    "Pita Pit NZ Secondary Schools Netball Champs Fin",
    "Pita Pit NZ Secondary Schools Netball Champs R1",
    "Pita Pit NZ Secondary Schools Netball Champs R2",
    "Secondary School Champs",
    "Taini Jamison Trophy",
    "Trans  Tasman U19",
    "Trans Tasman U19",
    "Trans- Tasman U19",
    "Trans-Tasman U19",
    "TransTasman U19"
  ],
  "afl_mens_leagues": [
    "AFL Finals",
    "AFL Season"
  ],
  "afl_womens_leagues": [
    "AFL Womens",
    "AFL Womens Finals",
    "AFLW",
    "Womens AFL Test"
  ]
}